LICENSE
README.md
pyproject.toml
setup.cfg
setup.py
benchmarl/__init__.py
benchmarl/eval_results.py
benchmarl/evaluate.py
benchmarl/hydra_config.py
benchmarl/resume.py
benchmarl/run.py
benchmarl/utils.py
benchmarl.egg-info/PKG-INFO
benchmarl.egg-info/SOURCES.txt
benchmarl.egg-info/dependency_links.txt
benchmarl.egg-info/requires.txt
benchmarl.egg-info/top_level.txt
benchmarl/algorithms/__init__.py
benchmarl/algorithms/common.py
benchmarl/algorithms/ensemble.py
benchmarl/algorithms/iddpg.py
benchmarl/algorithms/ippo.py
benchmarl/algorithms/iql.py
benchmarl/algorithms/isac.py
benchmarl/algorithms/maddpg.py
benchmarl/algorithms/mappo.py
benchmarl/algorithms/masac.py
benchmarl/algorithms/qmix.py
benchmarl/algorithms/vdn.py
benchmarl/algorithms/../conf/.DS_Store
benchmarl/algorithms/../conf/__init__.py
benchmarl/algorithms/../conf/config.yaml
benchmarl/algorithms/../conf/__pycache__/__init__.cpython-311.pyc
benchmarl/algorithms/../conf/__pycache__/__init__.cpython-39.pyc
benchmarl/algorithms/../conf/algorithm/iddpg.yaml
benchmarl/algorithms/../conf/algorithm/ippo.yaml
benchmarl/algorithms/../conf/algorithm/iql.yaml
benchmarl/algorithms/../conf/algorithm/isac.yaml
benchmarl/algorithms/../conf/algorithm/maddpg.yaml
benchmarl/algorithms/../conf/algorithm/mappo.yaml
benchmarl/algorithms/../conf/algorithm/masac.yaml
benchmarl/algorithms/../conf/algorithm/qmix.yaml
benchmarl/algorithms/../conf/algorithm/vdn.yaml
benchmarl/algorithms/../conf/experiment/base_experiment.yaml
benchmarl/algorithms/../conf/model/sequence.yaml
benchmarl/algorithms/../conf/model/layers/cnn.yaml
benchmarl/algorithms/../conf/model/layers/deepsets.yaml
benchmarl/algorithms/../conf/model/layers/gnn.yaml
benchmarl/algorithms/../conf/model/layers/gru.yaml
benchmarl/algorithms/../conf/model/layers/lstm.yaml
benchmarl/algorithms/../conf/model/layers/mlp.yaml
benchmarl/algorithms/../conf/task/.DS_Store
benchmarl/algorithms/../conf/task/magent/adversarial_pursuit.yaml
benchmarl/algorithms/../conf/task/meltingpot/allelopathic_harvest__open.yaml
benchmarl/algorithms/../conf/task/meltingpot/bach_or_stravinsky_in_the_matrix__arena.yaml
